demographer_popgen/__init__.py
demographer_popgen-0.0.0.dev20.dist-info/DESCRIPTION.rst
demographer_popgen-0.0.0.dev20.dist-info/METADATA
demographer_popgen-0.0.0.dev20.dist-info/RECORD
demographer_popgen-0.0.0.dev20.dist-info/WHEEL
demographer_popgen-0.0.0.dev20.dist-info/entry_points.txt
demographer_popgen-0.0.0.dev20.dist-info/metadata.json
demographer_popgen-0.0.0.dev20.dist-info/top_level.txt
