Metadata-Version: 2.0
Name: demographer-popgen
Version: 0.0.0.dev20
Summary: DemoGrapher: Software for graphically studying population histories.
Home-page: https://github.com/ejewett/demographer
Author: Ethan Jewett
Author-email: ejewett@gmail.com
License: GPL3.0
Platform: UNKNOWN
Classifier: Development Status :: 3 - Alpha
Classifier: Intended Audience :: End Users/Desktop
Classifier: License :: OSI Approved :: GNU General Public License v3 or later (GPLv3+)
Classifier: Programming Language :: Python :: 2.7
Classifier: Topic :: Scientific/Engineering :: Bio-Informatics
Requires-Dist: matplotlib
Requires-Dist: mpmath
Requires-Dist: numpy
Requires-Dist: scipy
